python_abraflexi/__init__.py
python_abraflexi/exceptions.py
python_abraflexi/read_only.py
python_abraflexi/read_write.py
python_abraflexi/relation.py
python_abraflexi-1.0.0.dist-info/licenses/LICENSE
python_abraflexi-1.0.0.dist-info/METADATA
python_abraflexi-1.0.0.dist-info/WHEEL
python_abraflexi-1.0.0.dist-info/top_level.txt
python_abraflexi-1.0.0.dist-info/RECORD
