Metadata-Version: 2.4
Name: python-abraflexi
Version: 1.0.0
Summary: Python library for AbraFlexi REST API
Home-page: https://github.com/VitexSoftware/python-abraflexi
Author: Vítězslav Dvořák
Author-email: Vítězslav Dvořák <info@vitexsoftware.cz>
License: MIT
Project-URL: Homepage, https://github.com/VitexSoftware/python-abraflexi
Project-URL: Repository, https://github.com/VitexSoftware/python-abraflexi
Project-URL: Issues, https://github.com/VitexSoftware/python-abraflexi/issues
Keywords: abraflexi,flexibee,api,rest,accounting,erp
Classifier: Development Status :: 4 - Beta
Classifier: Intended Audience :: Developers
Classifier: Topic :: Software Development :: Libraries :: Python Modules
Classifier: License :: OSI Approved :: MIT License
Classifier: Programming Language :: Python :: 3
Classifier: Programming Language :: Python :: 3.8
Classifier: Programming Language :: Python :: 3.9
Classifier: Programming Language :: Python :: 3.10
Classifier: Programming Language :: Python :: 3.11
Classifier: Programming Language :: Python :: 3.12
Requires-Python: >=3.8
License-File: LICENSE
Requires-Dist: requests>=2.28.0
Requires-Dist: python-dateutil>=2.8.0
Requires-Dist: urllib3>=1.26.0
Provides-Extra: dev
Requires-Dist: pytest>=7.0; extra == "dev"
Requires-Dist: pytest-cov>=3.0; extra == "dev"
Requires-Dist: black>=22.0; extra == "dev"
Requires-Dist: flake8>=4.0; extra == "dev"
Requires-Dist: mypy>=0.950; extra == "dev"
Dynamic: author
Dynamic: home-page
Dynamic: license-file
Dynamic: requires-python
